AUTHORS.rst
HISTORY.rst
LICENSE
MANIFEST.in
README.rst
requirements.txt
setup.cfg
setup.py
machete/__init__.py
machete/build.info
machete/start.py
machete.egg-info/PKG-INFO
machete.egg-info/SOURCES.txt
machete.egg-info/dependency_links.txt
machete.egg-info/entry_points.txt
machete.egg-info/requires.txt
machete.egg-info/top_level.txt
machete.egg-info/zip-safe
machete/submodule/__init__.py
machete/submodule/module.py
machete/templates/_base/.coveragerc
machete/templates/_base/.gitignore
machete/templates/_base/.travis.yml
machete/templates/_base/.venv
machete/templates/_base/AUTHORS.rst
machete/templates/_base/HISTORY.rst
machete/templates/_base/LICENSE
machete/templates/_base/README.rst
machete/templates/_base/requirements-dev.txt
machete/templates/_base/settings.py
machete/templates/_base/setup.cfg
machete/templates/_base/setup.py
machete/templates/_base/packagesample/__init__.py
machete/templates/_base/packagesample/build.info
machete/templates/_base/packagesample/modules/__init__.py
machete/templates/_base/packagesample/modules/module.py
machete/templates/_base/tests/__init__.py
machete/templates/_base/tests/tests_basic.py
machete/templates/app/MANIFEST.in
machete/templates/app/requirements.txt
machete/templates/app/run.py
machete/templates/app/packagesample/start.py
machete/templates/bootstrap/MANIFEST.in
machete/templates/bootstrap/requirements.txt
machete/templates/bootstrap/run.py
machete/templates/bootstrap/packagesample/start.py
machete/templates/bootstrap/packagesample/static/css/app.css
machete/templates/bootstrap/packagesample/static/js/app.js
machete/templates/bootstrap/packagesample/templates/_base.html
machete/templates/bootstrap/packagesample/templates/start.html
machete/templates/flask/MANIFEST.in
machete/templates/flask/requirements.txt
machete/templates/flask/run.py
machete/templates/flask/packagesample/start.py
machete/templates/flask/packagesample/static/css/app.css
machete/templates/flask/packagesample/static/js/app.js
machete/templates/flask/packagesample/templates/_base.html
machete/templates/flask/packagesample/templates/start.html