Metadata-Version: 1.1
Name: machete
Version: 0.0.5.100
Summary: A command-line tool to create projects                   from templates, to start your python work.
Home-page: https://github.com/marco.lovato/machete
Author: Marco Lovato
Author-email: maglovato@gmail.com
License: MIT
Download-URL: https://github.com/marco.lovato/machete/tarball/0.0.5.100
Platform: any
Classifier: Intended Audience :: Developers
Classifier: Programming Language :: Python :: 2.7
